setup.py
src/dogapi/__init__.py
src/dogapi/common.py
src/dogapi/constants.py
src/dogapi/exceptions.py
src/dogapi/fab.py
src/dogapi.egg-info/PKG-INFO
src/dogapi.egg-info/SOURCES.txt
src/dogapi.egg-info/dependency_links.txt
src/dogapi.egg-info/entry_points.txt
src/dogapi.egg-info/requires.txt
src/dogapi.egg-info/top_level.txt
src/dogapi/http/__init__.py
src/dogapi/http/alerts.py
src/dogapi/http/base.py
src/dogapi/http/dashes.py
src/dogapi/http/events.py
src/dogapi/http/infrastructure.py
src/dogapi/http/metrics.py
src/dogapi/http/monitors.py
src/dogapi/http/screenboards.py
src/dogapi/http/service_check.py
src/dogapi/http/snapshot.py
src/dogapi/http/users.py
src/dogapi/stats/__init__.py
src/dogapi/stats/dog_stats_api.py
src/dogapi/stats/metrics.py
src/dogapi/stats/periodic_timer.py
src/dogapi/stats/reporters.py
src/dogapi/stats/statsd.py
src/dogshell/__init__.py
src/dogshell/comment.py
src/dogshell/common.py
src/dogshell/dashboard.py
src/dogshell/event.py
src/dogshell/metric.py
src/dogshell/search.py
src/dogshell/tag.py
src/dogshell/wrap.py