Metadata-Version: 1.0
Name: dogapi
Version: 1.9.0
Summary: Python bindings to Datadog's API and a user-facing command line tool.
Home-page: http://www.datadoghq.com
Author: Datadog, Inc.
Author-email: packages@datadoghq.com
License: BSD
Keywords: datadog data
Platform: UNKNOWN
